{
	"contexts": [],
	"displayType": "page",
	"entityPermissions": {
		"deleteUserIds": [],
		"readUserIds": [],
		"writeUserIds": []
	},
	"gridItems": [
		{
			"cols": 100,
			"rows": 1,
			"weight": 0,
			"x": 0,
			"y": 0
		}
	],
	"id": "bd4c1820-952c-47c8-9478-5a49d45a7bc0",
	"interactions": {
		"interactions": {
			"listeners": []
		}
	},
	"layoutSetting": {
		"settings": []
	},
	"layoutType": "split",
	"panels": [
		{
			"columnSetting": {
				"settings": []
			},
			"panes": [],
			"settings": [],
			"stylePlugin": ""
		}
	],
	"persistence": {
		"dataduct": {
			"settings": []
		}
	},
	"rowSettings": [
		{
			"settings": []
		}
	],
	"site": "spearhead",
	"userId": "44e8b438-a061-70ca-faa7-3d3e93c015cb"
}
